koubou/__init__.py
koubou/cli.py
koubou/config.py
koubou/config_tree.py
koubou/dependency_analyzer.py
koubou/exceptions.py
koubou/generator.py
koubou/live_generator.py
koubou/localization.py
koubou/watcher.py
koubou/appstore/__init__.py
koubou/appstore/auth.py
koubou/appstore/client.py
koubou/appstore/uploader.py
koubou/frames/Frames.json
koubou/frames/MacBook Air 2020.png
koubou/frames/MacBook Air 2022.png
koubou/frames/MacBook Pro 2021 14.png
koubou/frames/MacBook Pro 2021 16.png
koubou/frames/Sizes.json
koubou/frames/Watch Series 4 40.png
koubou/frames/Watch Series 4 44.png
koubou/frames/Watch Series 7 45 Midnight.png
koubou/frames/Watch Series 7 45 Starlight.png
koubou/frames/Watch Ultra 2022.png
koubou/frames/iMac 2021.png
"koubou/frames/iMac 24"" - Silver.png"
koubou/frames/iPad - Silver - Landscape.png
koubou/frames/iPad - Silver - Portrait.png
koubou/frames/iPad 2021 Landscape.png
koubou/frames/iPad 2021 Portrait.png
"koubou/frames/iPad Air 11"" - M2 - Blue - Landscape.png"
"koubou/frames/iPad Air 11"" - M2 - Blue - Portrait.png"
"koubou/frames/iPad Air 11"" - M2 - Purple - Landscape.png"
"koubou/frames/iPad Air 11"" - M2 - Purple - Portrait.png"
"koubou/frames/iPad Air 11"" - M2 - Space Gray - Landscape.png"
"koubou/frames/iPad Air 11"" - M2 - Space Gray - Portrait.png"
"koubou/frames/iPad Air 11"" - M2 - Stardust - Landscape.png"
"koubou/frames/iPad Air 11"" - M2 - Stardust - Portrait.png"
"koubou/frames/iPad Air 13"" - M2 - Blue - Landscape.png"
"koubou/frames/iPad Air 13"" - M2 - Blue - Portrait.png"
"koubou/frames/iPad Air 13"" - M2 - Purple - Landscape.png"
"koubou/frames/iPad Air 13"" - M2 - Purple - Portrait.png"
"koubou/frames/iPad Air 13"" - M2 - Space Gray - Landscape.png"
"koubou/frames/iPad Air 13"" - M2 - Space Gray - Portrait.png"
"koubou/frames/iPad Air 13"" - M2 - Stardust - Landscape.png"
"koubou/frames/iPad Air 13"" - M2 - Stardust - Portrait.png"
koubou/frames/iPad Air 2020 Landscape.png
koubou/frames/iPad Air 2020 Portrait.png
koubou-0.8.3.dist-info/licenses/LICENSE
koubou-0.8.3.dist-info/METADATA
koubou-0.8.3.dist-info/WHEEL
koubou-0.8.3.dist-info/entry_points.txt
koubou-0.8.3.dist-info/top_level.txt
koubou-0.8.3.dist-info/RECORD
