Metadata-Version: 2.4
Name: koubou
Version: 0.8.3
Summary: 🎯 Koubou (工房) - The artisan workshop for App Store screenshots
Author-email: David Collado <your-email@example.com>
License: MIT License
Project-URL: Homepage, https://github.com/bitomule/koubou
Project-URL: Repository, https://github.com/bitomule/koubou
Project-URL: Documentation, https://koubou.readthedocs.io
Project-URL: Issues, https://github.com/bitomule/koubou/issues
Keywords: screenshot,app-store,graphics,automation,artisan,koubou
Classifier: Development Status :: 4 - Beta
Classifier: Intended Audience :: Developers
Classifier: License :: OSI Approved :: MIT License
Classifier: Operating System :: OS Independent
Classifier: Programming Language :: Python :: 3
Classifier: Programming Language :: Python :: 3.9
Classifier: Programming Language :: Python :: 3.10
Classifier: Programming Language :: Python :: 3.11
Classifier: Programming Language :: Python :: 3.12
Classifier: Topic :: Multimedia :: Graphics
Classifier: Topic :: Software Development :: Build Tools
Requires-Python: >=3.9
License-File: LICENSE
Requires-Dist: Pillow>=10.0.0
Requires-Dist: PyYAML>=6.0
Requires-Dist: click>=8.0.0
Requires-Dist: pydantic>=2.0.0
Requires-Dist: rich>=13.0.0
Requires-Dist: typer>=0.9.0
Requires-Dist: watchdog>=3.0.0
Requires-Dist: pyjwt>=2.8.0
Requires-Dist: cryptography>=41.0.0
Requires-Dist: httpx>=0.25.0
Provides-Extra: dev
Requires-Dist: pytest>=7.0.0; extra == "dev"
Requires-Dist: pytest-cov>=4.0.0; extra == "dev"
Requires-Dist: black>=23.0.0; extra == "dev"
Requires-Dist: isort>=5.0.0; extra == "dev"
Requires-Dist: flake8>=6.0.0; extra == "dev"
Requires-Dist: mypy>=1.0.0; extra == "dev"
Requires-Dist: pre-commit>=3.0.0; extra == "dev"
Requires-Dist: responses>=0.24.0; extra == "dev"
Requires-Dist: pytest-httpx>=0.26.0; extra == "dev"
Dynamic: license-file
